{"episode_list":[{"episode_id":"1","episode_name":"\u8352\u6728\u6bd4\u5948Vi\uff9a\uff6f\uff7d\uff9d\uff74\uff8b\uff9f\uff7f\uff70\uff84\uff9e1","episode_voice":"0"},{"episode_id":"2","episode_name":"\u8352\u6728\u6bd4\u5948Vo\uff9a\uff6f\uff7d\uff9d\uff74\uff8b\uff9f\uff7f\uff70\uff84\uff9e1","episode_voice":"0"},{"episode_id":"3","episode_name":"\u8352\u6728\u6bd4\u5948Da\uff9a\uff6f\uff7d\uff9d\uff74\uff8b\uff9f\uff7f\uff70\uff84\uff9e1","episode_voice":"0"},{"episode_id":"4","episode_name":"\u8352\u6728\u6bd4\u5948\uff7d\uff83\uff6f\uff8c\uff9f\uff71\uff6f\uff8c\uff9f\uff74\uff8b\uff9f\uff7f\uff70\uff84\uff9e1","episode_voice":"0"},{"episode_id":"5","episode_name":"\u8352\u6728\u6bd4\u5948Vi\uff9a\uff6f\uff7d\uff9d\uff74\uff8b\uff9f\uff7f\uff70\uff84\uff9e2","episode_voice":"0"},{"episode_id":"6","episode_name":"\u8352\u6728\u6bd4\u5948Vo\uff9a\uff6f\uff7d\uff9d\uff74\uff8b\uff9f\uff7f\uff70\uff84\uff9e2","episode_voice":"0"}],"idol_message":"\uff8c\uff9c\u3063\u3068\u3057\u305f\u670d\u3063\u3066\uff64\u304b\u308f\u3044\u3044\u3063\uff7d\u3088\u306d\u3047\uff5e\uff61\u2026\u4f3c\u5408\u3046\u304b\u4f3c\u5408\u308f\u306a\u3044\u304b\u306f\u7f6e\u3044\u3066\u304a\u3044\u3066","idol_attribute":"2"}